bootstrap_cfn/__init__.py
bootstrap_cfn/autoscale.py
bootstrap_cfn/cloudformation.py
bootstrap_cfn/config.py
bootstrap_cfn/config_defaults.yaml
bootstrap_cfn/diff.py
bootstrap_cfn/ec2.py
bootstrap_cfn/elb.py
bootstrap_cfn/errors.py
bootstrap_cfn/fab_tasks.py
bootstrap_cfn/iam.py
bootstrap_cfn/mime_packer.py
bootstrap_cfn/r53.py
bootstrap_cfn/utils.py
bootstrap_cfn/vpc.py
bootstrap_cfn-1.5.4.dist-info/METADATA
bootstrap_cfn-1.5.4.dist-info/RECORD
bootstrap_cfn-1.5.4.dist-info/WHEEL
bootstrap_cfn-1.5.4.dist-info/top_level.txt
