Metadata-Version: 2.1
Name: bootstrap-cfn
Version: 1.5.4
Summary: MOJDS cloudformation bootstrap tool
Home-page: http://github.com/ministryofjustice/bootstrap_cfn/
Author: MOJDS
Author-email: tools@digital.justice.gov.uk
License: LICENSE
Platform: any
Classifier: Development Status :: 5 - Production/Stable
Classifier: Environment :: Web Environment
Classifier: Intended Audience :: System Administrators
Classifier: Intended Audience :: Developers
Classifier: Operating System :: OS Independent
Classifier: Programming Language :: Python
Classifier: Programming Language :: Python :: 2
Classifier: Programming Language :: Python :: 2.6
Classifier: Programming Language :: Python :: 2.7
Classifier: Topic :: Software Development :: Libraries :: Python Modules
Requires-Dist: Fabric (>=1.10.1)
Requires-Dist: PyYAML (>=3.11)
Requires-Dist: boto (>=2.36.0)
Requires-Dist: boto3 (>=1.2.2)
Requires-Dist: dnspython (>=1.12.0)
Requires-Dist: netaddr (>=0.7.18)
Requires-Dist: troposphere (>=1.0.0)
Requires-Dist: datadiff (==2.0.0)
